pdm_hello-0.0.1.dist-info/METADATA
pdm_hello-0.0.1.dist-info/WHEEL
pdm_hello/__init__.py
pdm_hello/name.py
pdm_hello-0.0.1.dist-info/RECORD
