Metadata-Version: 2.1
Name: pdm-hello
Version: 0.0.1
Summary: buat hello library
Author-Email: Ircham Aji Nugroho <irchamajin@gmail.com>
License: MIT
Requires-Python: >=3.12
